ASR/__init__.py
ASR/keep_alive.py
ASR/nemo_asr.py
ASR/seamless_asr.py
ASR/vosk_asr.py
ASR/whisper_asr.py
ASR/whisperx_asr.py
Speak2Subs/__init__.py
Speak2Subs/cli.py
Speak2Subs/container_manager.py
Speak2Subs/media.py
Speak2Subs/post_processing.py
Speak2Subs/speak2subs.py
Speak2Subs/subtitle_tokens.py
Speak2Subs/vad.py
Speak2Subs/vtt_evaluator.py
Speak2Subs/vtt_loader.py
Speak2Subs-1.3.dist-info/METADATA
Speak2Subs-1.3.dist-info/WHEEL
Speak2Subs-1.3.dist-info/entry_points.txt
Speak2Subs-1.3.dist-info/top_level.txt
Speak2Subs-1.3.dist-info/RECORD
