Metadata-Version: 2.1
Name: Speak2Subs
Version: 1.3
Summary: TFM
Home-page: https://github.com/yourusername/my_package
Author: Julio Antonio Fresneda Garcia
Author-email: julioantonio.fresnedagarcia@gmail.com
Requires-Dist: moviepy
Requires-Dist: jiwer
Requires-Dist: pandas
Requires-Dist: pydub
Requires-Dist: noisereduce
Requires-Dist: art
